carolstats/__init__.py
carolstats/carol.py
carolstats-2.0.1.dist-info/LICENSE
carolstats-2.0.1.dist-info/METADATA
carolstats-2.0.1.dist-info/WHEEL
carolstats-2.0.1.dist-info/top_level.txt
carolstats-2.0.1.dist-info/RECORD
