Metadata-Version: 2.1
Name: carolstats
Version: 2.0.1
Summary: A package for manipulating statistical data in data science
Home-page: https://github.com/pypa/sampleproject
Author: Cássio Reis
Author-email: cassio.reis@engenharia.ufjf.br
License: UNKNOWN
Project-URL: Bug Tracker, https://github.com/pypa/sampleproject/issues
Platform: UNKNOWN
Classifier: Programming Language :: Python :: 3
Classifier: License :: OSI Approved :: MIT License
Classifier: Operating System :: OS Independent
Requires-Python: >=3.6
License-File: LICENSE
